
{
  "guardian": [
    {
      "phoneNumber": 9871274,
      "name": "Juan",
      "age": 35,
      "email": "micehejrjr"
    },
    {
      "phoneNumber": 9876533,
      "name": "Pedro",
      "age": 45,
      "email": "stevenriva@gmail.com"
    },
    {
      "phoneNumber": 4847588,
      "name": "jos",
      "age": 24,
      "email": "mdkdjgjti@gmail.com"
    },
    {
      "phoneNumber": 345670,
      "name": "paul",
      "age": 0,
      "email": "juan"
    },
    {
      "phoneNumber": 89765467,
      "name": "pepe",
      "age": 68,
      "email": "vghbjbtvtj457"
    }
  ]
}